 {
  "x" : "-0.12515153",
  "z" : "0.06178803",
  "y" : "-0.04094377",
  "color" : "red"
}{
  "y" : "-0.041205205",
  "z" : "0.061508007",
  "color" : "red",
  "x" : "-0.12623957"
}{
  "z" : "0.06143866",
  "color" : "red",
  "y" : "-0.041322965",
  "x" : "-0.12677701"
}{
  "x" : "-0.12745175",
  "color" : "red",
  "y" : "-0.04142641",
  "z" : "0.061117835"
}{
  "color" : "red",
  "y" : "-0.04160387",
  "x" : "-0.12838085",
  "z" : "0.060823757"
}{
  "z" : "0.060071558",
  "color" : "red",
  "x" : "-0.1291501",
  "y" : "-0.041618053"
}{
  "color" : "red",
  "x" : "-0.12981905",
  "z" : "0.05980398",
  "y" : "-0.041699313"
}{
  "z" : "0.05961215",
  "color" : "red",
  "y" : "-0.04179902",
  "x" : "-0.13049006"
}{
  "color" : "red",
  "x" : "-0.13145275",
  "y" : "-0.042100303",
  "z" : "0.05993348"
}{
  "color" : "red",
  "x" : "-0.13174881",
  "y" : "-0.042318992",
  "z" : "0.06048687"
}{
  "x" : "-0.13236307",
  "y" : "-0.04246827",
  "color" : "red",
  "z" : "0.06048537"
}{
  "color" : "red",
  "y" : "-0.042726",
  "x" : "-0.13288748",
  "z" : "0.06091742"
}{
  "y" : "-0.04295532",
  "color" : "red",
  "x" : "-0.13344684",
  "z" : "0.061163038"
}{
  "y" : "-0.043190755",
  "z" : "0.06166472",
  "color" : "red",
  "x" : "-0.13375251"
}{
  "x" : "-0.13432138",
  "z" : "0.06181256",
  "color" : "red",
  "y" : "-0.04341564"
}{
  "y" : "-0.04380373",
  "x" : "-0.13480276",
  "z" : "0.062464982",
  "color" : "red"
}{
  "color" : "red",
  "z" : "0.06301466",
  "x" : "-0.13508792",
  "y" : "-0.044083446"
}{
  "x" : "-0.13534647",
  "color" : "red",
  "y" : "-0.04444211",
  "z" : "0.06375062"
}{
  "color" : "red",
  "x" : "-0.13563028",
  "y" : "-0.04475321",
  "z" : "0.064264424"
}{
  "z" : "0.06500468",
  "y" : "-0.045107253",
  "x" : "-0.13588548",
  "color" : "red"
}{
  "color" : "red",
  "x" : "-0.13568252",
  "z" : "0.06585798",
  "y" : "-0.045319423"
}{
  "color" : "red",
  "x" : "-0.13578765",
  "y" : "-0.045557853",
  "z" : "0.066343315"
}{
  "x" : "-0.13558505",
  "y" : "-0.045779996",
  "z" : "0.06719676",
  "color" : "red"
}{
  "z" : "0.06803561",
  "color" : "red",
  "y" : "-0.04589134",
  "x" : "-0.13520364"
}{
  "x" : "-0.13483347",
  "y" : "-0.04596747",
  "z" : "0.06876066",
  "color" : "red"
}{
  "color" : "red",
  "x" : "-0.13441713",
  "y" : "-0.0462103",
  "z" : "0.06980247"
}{
  "y" : "-0.046510484",
  "color" : "red",
  "x" : "-0.13406286",
  "z" : "0.07056182"
}{
  "y" : "-0.04688474",
  "x" : "-0.13373885",
  "z" : "0.07124932",
  "color" : "red"
}{
  "x" : "-0.13340391",
  "y" : "-0.047258493",
  "z" : "0.07194434",
  "color" : "red"
}{
  "x" : "-0.13288373",
  "y" : "-0.04744538",
  "color" : "red",
  "z" : "0.0725752"
}{
  "y" : "-0.04772389",
  "color" : "red",
  "x" : "-0.13256364",
  "z" : "0.073174864"
}{
  "y" : "-0.047949865",
  "color" : "red",
  "x" : "-0.13226973",
  "z" : "0.073688276"
}{
  "y" : "-0.048292518",
  "color" : "red",
  "x" : "-0.13194941",
  "z" : "0.074363045"
}{
  "color" : "red",
  "x" : "-0.1314503",
  "z" : "0.07500034",
  "y" : "-0.04847912"
}{
  "x" : "-0.13135666",
  "y" : "-0.048758954",
  "z" : "0.07543929",
  "color" : "red"
}{
  "y" : "-0.04898419",
  "color" : "red",
  "x" : "-0.13104749",
  "z" : "0.07601171"
}{
  "color" : "red",
  "z" : "0.07661932",
  "x" : "-0.13073602",
  "y" : "-0.04934008"
}{
  "z" : "0.07709347",
  "x" : "-0.13045405",
  "y" : "-0.049576305",
  "color" : "red"
}{
  "z" : "0.0775317",
  "color" : "red",
  "x" : "-0.13020422",
  "y" : "-0.04977275"
}{
  "x" : "-0.1298679",
  "y" : "-0.05019517",
  "z" : "0.07835002",
  "color" : "red"
}{
  "y" : "-0.050399054",
  "x" : "-0.12956786",
  "color" : "red",
  "z" : "0.078898914"
}{
  "x" : "-0.12930961",
  "y" : "-0.05055033",
  "z" : "0.079346016",
  "color" : "red"
}{
  "x" : "-0.12901117",
  "z" : "0.079891294",
  "y" : "-0.05075414",
  "color" : "red"
}{
  "x" : "-0.12852855",
  "y" : "-0.05115949",
  "color" : "red",
  "z" : "0.08050012"
}{
  "z" : "0.08082013",
  "color" : "red",
  "x" : "-0.12806453",
  "y" : "-0.05117309"
}{
  "z" : "0.081141844",
  "y" : "-0.051464904",
  "x" : "-0.12782331",
  "color" : "red"
}{
  "x" : "-0.12736928",
  "y" : "-0.05145879",
  "z" : "0.0814429",
  "color" : "red"
}{
  "y" : "-0.05170094",
  "color" : "red",
  "x" : "-0.12690356",
  "z" : "0.08189641"
}{
  "color" : "red",
  "y" : "-0.051596716",
  "x" : "-0.12640795",
  "z" : "0.08216502"
}{
  "x" : "-0.12594356",
  "y" : "-0.051837973",
  "z" : "0.08261799",
  "color" : "red"
}{
  "color" : "red",
  "x" : "-0.12547347",
  "y" : "-0.051723212",
  "z" : "0.08287202"
}{
  "color" : "red",
  "x" : "-0.12501971",
  "z" : "0.08322274",
  "y" : "-0.051797517"
}{
  "x" : "-0.12421669",
  "y" : "-0.051768906",
  "z" : "0.0837521",
  "color" : "red"
}{
  "y" : "-0.05159973",
  "color" : "red",
  "x" : "-0.12358065",
  "z" : "0.084068246"
}{
  "color" : "red",
  "y" : "-0.05140079",
  "x" : "-0.122498296",
  "z" : "0.08457131"
}{
  "z" : "0.084876515",
  "y" : "-0.05129023",
  "color" : "red",
  "x" : "-0.121852666"
}{
  "color" : "red",
  "x" : "-0.12121214",
  "y" : "-0.051051352",
  "z" : "0.0851119"
}{
  "color" : "red",
  "z" : "0.08539168",
  "x" : "-0.12057398",
  "y" : "-0.05095121"
}{
  "x" : "-0.11971417",
  "z" : "0.085742936",
  "y" : "-0.05075445",
  "color" : "red"
}{
  "color" : "red",
  "z" : "0.086029",
  "y" : "-0.050651785",
  "x" : "-0.11907622"
}{
  "z" : "0.086285956",
  "color" : "red",
  "x" : "-0.11846634",
  "y" : "-0.0505198"
}{
  "color" : "red",
  "x" : "-0.117835306",
  "z" : "0.08648473",
  "y" : "-0.050246548"
}{
  "color" : "red",
  "z" : "0.08664727",
  "y" : "-0.049913105",
  "x" : "-0.11720654"
}{
  "color" : "red",
  "y" : "-0.049638078",
  "x" : "-0.11657547",
  "z" : "0.08685148"
}{
  "color" : "red",
  "x" : "-0.11593216",
  "z" : "0.08700568",
  "y" : "-0.0492451"
}{
  "y" : "-0.04885229",
  "z" : "0.086982615",
  "x" : "-0.11552898",
  "color" : "red"
}{
  "color" : "red",
  "x" : "-0.11489459",
  "y" : "-0.048446946",
  "z" : "0.08704252"
}{
  "x" : "-0.114327304",
  "color" : "red",
  "z" : "0.08681504",
  "y" : "-0.047769304"
}{
  "y" : "-0.047260247",
  "x" : "-0.113733694",
  "z" : "0.0867041",
  "color" : "red"
}{
  "z" : "0.08635505",
  "x" : "-0.113358356",
  "color" : "red",
  "y" : "-0.0466468"
}{
  "color" : "red",
  "y" : "-0.046157833",
  "x" : "-0.11325295",
  "z" : "0.085870825"
}{
  "color" : "red",
  "x" : "-0.11314695",
  "y" : "-0.045581013",
  "z" : "0.08522588"
}{
  "y" : "-0.04501903",
  "x" : "-0.11304752",
  "z" : "0.08454796",
  "color" : "red"
}{
  "y" : "-0.04459864",
  "z" : "0.084056936",
  "x" : "-0.11292141",
  "color" : "red"
}{
  "color" : "red",
  "x" : "-0.11278643",
  "y" : "-0.044201206",
  "z" : "0.08360096"
}{
  "x" : "-0.11270782",
  "color" : "red",
  "z" : "0.082749665",
  "y" : "-0.04359384"
}{
  "x" : "-0.11283756",
  "color" : "red",
  "z" : "0.081872724",
  "y" : "-0.0430519"
}{
  "z" : "0.081247196",
  "x" : "-0.11293019",
  "color" : "red",
  "y" : "-0.04267308"
}{
  "color" : "red",
  "z" : "0.08030417",
  "x" : "-0.11325642",
  "y" : "-0.042158026"
}{
  "color" : "red",
  "x" : "-0.11360369",
  "y" : "-0.041896474",
  "z" : "0.07937044"
}{
  "x" : "-0.11403874",
  "color" : "red",
  "y" : "-0.041759074",
  "z" : "0.078112766"
}{
  "y" : "-0.041657194",
  "z" : "0.0765612",
  "x" : "-0.114902765",
  "color" : "red"
}{
  "color" : "red",
  "x" : "-0.11554797",
  "y" : "-0.041474607",
  "z" : "0.07503302"
}{
  "y" : "-0.041452255",
  "color" : "red",
  "x" : "-0.116292335",
  "z" : "0.074182294"
}{
  "color" : "red",
  "y" : "-0.04136224",
  "x" : "-0.11686071",
  "z" : "0.07333482"
}{
  "y" : "-0.04122475",
  "z" : "0.07193253",
  "x" : "-0.11789539",
  "color" : "red"
}{
  "x" : "-0.118902795",
  "y" : "-0.041060716",
  "z" : "0.07064861",
  "color" : "red"
}{
  "color" : "red",
  "y" : "-0.040864315",
  "z" : "0.069394015",
  "x" : "-0.119707786"
}{
  "z" : "0.06863781",
  "color" : "red",
  "x" : "-0.12062392",
  "y" : "-0.04091069"
}{
  "y" : "-0.04093139",
  "z" : "0.06735457",
  "x" : "-0.12165908",
  "color" : "red"
}{
  "x" : "-0.12229633",
  "y" : "-0.04104041",
  "z" : "0.066981204",
  "color" : "red"
}{
  "x" : "-0.12317244",
  "z" : "0.06638565",
  "color" : "red",
  "y" : "-0.04117529"
}{
  "y" : "-0.041335516",
  "z" : "0.06576646",
  "color" : "red",
  "x" : "-0.12409041"
}{
  "y" : "-0.04151332",
  "color" : "red",
  "z" : "0.06501616",
  "x" : "-0.12503955"
}{
  "x" : "-0.1257337",
  "color" : "red",
  "z" : "0.064518444",
  "y" : "-0.041651428"
}{
  "color" : "red",
  "z" : "0.06449631",
  "x" : "-0.12634452",
  "y" : "-0.041840862"
}